{
  "project_info": {
    "project_number": "69403980408",
    "firebase_url": "https://slots-tracker-mobile-app.firebaseio.com",
    "project_id": "slots-tracker-mobile-app",
    "storage_bucket": "slots-tracker-mobile-app.appspot.com"
  },
  "client": [
    {
      "client_info": {
        "mobilesdk_app_id": "1:69403980408:android:5f9d50fad8a7f69a46738d",
        "android_client_info": {
          "package_name": "com.slots"
        }
      },
      "oauth_client": [
        {
          "client_id": "69403980408-j1tmqrbgcmh7ae14aj8rm250bp34ebvn.apps.googleusercontent.com",
          "client_type": 3
        }
      ],
      "api_key": [
        {
          "current_key": "AIzaSyAovBgefSyPBITZTvF33lJY6bF0PVRz5g8"
        }
      ],
      "services": {
        "appinvite_service": {
          "other_platform_oauth_client": [
            {
              "client_id": "69403980408-j1tmqrbgcmh7ae14aj8rm250bp34ebvn.apps.googleusercontent.com",
              "client_type": 3
            }
          ]
        }
      }
    }
  ],
  "configuration_version": "1"
}